brickllm/__init__.py
brickllm/compiled_graphs.py
brickllm/configs.py
brickllm/edges/__init__.py
brickllm/edges/check_sensor_presence.py
brickllm/edges/validate_condition.py
brickllm/edges/validate_condition_local.py
brickllm/graphs/__init__.py
brickllm/graphs/abstract_graph.py
brickllm/graphs/brickschema_graph.py
brickllm/graphs/brickschema_graph_local.py
brickllm/helpers/__init__.py
brickllm/helpers/llm_models.py
brickllm/helpers/prompts.py
brickllm/logger.py
brickllm/nodes/__init__.py
brickllm/nodes/generation_local.py
brickllm/nodes/get_elem_children.py
brickllm/nodes/get_elements.py
brickllm/nodes/get_relationships.py
brickllm/nodes/get_sensors.py
brickllm/nodes/schema_to_ttl.py
brickllm/nodes/validate_schema.py
brickllm/ontologies/Brick.ttl
brickllm/ontologies/__init__.py
brickllm/ontologies/brick_hierarchy.json
brickllm/schemas.py
brickllm/states.py
brickllm/utils/__init__.py
brickllm/utils/get_hierarchy_info.py
brickllm/utils/query_brickschema.py
brickllm/utils/rdf_parser.py
brickllm/utils/ttl_to_prompt.py
brickllm-1.3.0.dist-info/LICENSE
brickllm-1.3.0.dist-info/METADATA
brickllm-1.3.0.dist-info/WHEEL
brickllm-1.3.0.dist-info/RECORD
