Metadata-Version: 2.1
Name: brickllm
Version: 1.3.0
Summary: Library for generating RDF files following BrickSchema ontology using LLM
Home-page: https://brickllm.com/
License: BSD-3-Clause
Keywords: brickllm,brickschema,rdf,ontologies,knowledge graph,semantic web,ai,artificial intelligence,gpt,machine learning,natural language processing,nlp,openai,building automation,iot,graph,ontology
Author: Marco Perini
Author-email: marco.perini@eurac.edu
Requires-Python: >=3.9,<4.0
Classifier: Intended Audience :: Developers
Classifier: License :: OSI Approved :: BSD License
Classifier: Operating System :: OS Independent
Classifier: Programming Language :: Python :: 3
Classifier: Programming Language :: Python :: 3.9
Classifier: Programming Language :: Python :: 3.10
Classifier: Programming Language :: Python :: 3.11
Classifier: Programming Language :: Python :: 3.12
Classifier: Programming Language :: Python :: 3.13
Classifier: Topic :: Software Development :: Libraries :: Python Modules
Requires-Dist: langchain-anthropic (==0.2.1)
Requires-Dist: langchain-fireworks (==0.2.0)
Requires-Dist: langchain-ollama (>=0.2.2,<0.3.0)
Requires-Dist: langchain_community (==0.3.0)
Requires-Dist: langchain_core (>=0.3.5,<0.4.0)
Requires-Dist: langchain_openai (==0.2.0)
Requires-Dist: langgraph (==0.2.23)
Requires-Dist: pyshacl (==0.21)
Requires-Dist: python-dotenv (>=1.0.1,<2.0.0)
Requires-Dist: rdflib (>=6.2.0,<7)
Project-URL: Documentation, https://brickllm.com/docs
Project-URL: Repository, https://github.com/EURAC-EEBgroup/brickllm-lib
